<?xml version="1.0" encoding="UTF-8"?>
<objects serializationModel="Studio.02.02.00">
	<object class="AudioFile" id="{e151f5c0-8f64-4bf4-a973-6b95a2512521}">
		<property name="assetPath">
			<value>CyberLeaf-ModernUISFX/SlidesAndTransitions/SwooshSlide2.wav</value>
		</property>
		<property name="frequencyInKHz">
			<value>44.0999985</value>
		</property>
		<property name="channelCount">
			<value>2</value>
		</property>
		<property name="length">
			<value>1.0929931972789115</value>
		</property>
		<relationship name="masterAssetFolder">
			<destination>{824259a3-0fe1-4931-8e90-6bdfeff423c6}</destination>
		</relationship>
	</object>
</objects>
